Metadata-Version: 1.0
Name: prog-work
Version: 1.0
Summary: Work with arithmetic and geometrical progression
Home-page: UNKNOWN
Author: UNKNOWN
Author-email: timur20041229@gmail.com
License: UNKNOWN
Platform: UNKNOWN
